mifc_mcp_server/__init__.py
mifc_mcp_server/server.py
mifc_mcp_server-2.0.0.dist-info/METADATA
mifc_mcp_server-2.0.0.dist-info/WHEEL
mifc_mcp_server-2.0.0.dist-info/entry_points.txt
mifc_mcp_server-2.0.0.dist-info/RECORD
