Metadata-Version: 2.4
Name: mifc-mcp-server
Version: 2.0.0
Summary: MIFC助手
Requires-Python: >=3.12
Requires-Dist: bs4>=0.0.2
Requires-Dist: dashscope>=1.23.5
Requires-Dist: dotenv>=0.9.9
Requires-Dist: httpx>=0.28.1
Requires-Dist: mcp[cli]>=1.9.4
Requires-Dist: mcp~=1.9.4
Requires-Dist: pydantic~=2.11.7
Requires-Dist: requests~=2.32.4
